ver/decode_reg_inst.sv
`ifndef FILE_INCL
    `define FILE_INCL
    `include "processor_defines.sv"
`endif

module decode_reg_inst(
    input  logic [31:7] instruction_code,
    output logic [4:0] rs1,
    output logic [4:0] rs2,
    output logic [4:0] rd,
    output logic [4:0] alu_control
);

logic [2:0] func3;
logic [6:0] func7;

always_comb begin
    rs1 = instruction_code[19:15];
    rs2 = instruction_code[24:20];
    func3 = instruction_code[14:12];
    func7 = instruction_code[31:25];
    rd = instruction_code[11:7];

    case (func3)
        3'h0: begin
            if (func7==7'h00) alu_control = `ADD;
            else if (func7==7'h20)  alu_control = `SUB;
            else alu_control = `ALU_NOP;
            end
        3'h1: if (func7 == 7'h00) alu_control = `SLL;
              else alu_control = `ALU_NOP;
        3'h2: if (func7 == 7'h00) alu_control = `SLT;
              else alu_control = `ALU_NOP;
        3'h3: if (func7 == 7'h00) alu_control = `SLTU;
              else alu_control = `ALU_NOP;
        3'h4: if (func7 == 7'h00) alu_control = `XOR;
              else alu_control = `ALU_NOP;
         3'h5: begin
            if (func7==7'h00) alu_control = `SRL;
            else if (func7==7'h20)  alu_control = `SRA;
            else alu_control = `ALU_NOP;
            end
        3'h6: if (func7 == 7'h00) alu_control = `OR;
              else alu_control = `ALU_NOP;
        3'h7: if (func7 == 7'h00) alu_control = `AND;
              else alu_control = `ALU_NOP;
        default: alu_control = `ALU_NOP;
    endcase
end

`ifndef SUBMODULE_DISABLE_WAVES
initial begin
    $dumpfile("./sim_build/decode_reg_inst.vcd");
    $dumpvars(0, decode_reg_inst);
end
`endif

endmodule

sim_submodules/sim_build/decode_reg_inst.vcd
$date
	Fri Jul  5 14:06:00 2024
$end
$version
	Icarus Verilog
$end
$timescale
	1ps
$end
$scope module decode_reg_inst $end
$var wire 25 ! instruction_code [31:7] $end
$var reg 5 " alu_control [4:0] $end
$var reg 3 # func3 [2:0] $end
$var reg 7 $ func7 [6:0] $end
$var reg 5 % rd [4:0] $end
$var reg 5 & rs1 [4:0] $end
$var reg 5 ' rs2 [4:0] $end
$upscope $end
$enddefinitions $end
$comment Show the parameter values. $end
$dumpall
$end
#0
$dumpvars
b100 '
b10111 &
b10100 %
b100000 $
b110 #
b0 "
b100000001001011111010100 !
$end
#1000
b110 "
b1 %
b0 $
b1 #
b1 '
b11011 &
b11101100100001 !
#2000
b11 "
b10101 %
b100 #
b1100 '
b10000 &
b11001000010010101 !
#3000
b110 "
b10110 %
b1 #
b10000 '
b11110 &
b100001111000110110 !
#4000
b111 "
b1100 %
b101 #
b11000 '
b110001111010101100 !
#5000
b1 "
b1000 %
b0 #
b0 '
b1010 &
b101000001000 !
#6000
b0 "
b10010 %
b100000 $
b11 #
b11011 '
b11 &
b100000110110001101110010 !
#7000
b11000 %
b11001 '
b10110 &
b100000110011011001111000 !
#8000
b111 "
b10111 %
b0 $
b101 #
b110011011010110111 !
#9000
b1001 "
b10010 %
b10 #
b111 '
b10011 &
b1111001101010010 !
#10000
b0 "
b1101 %
b100000 $
b1 #
b1001 '
b1011 &
b100000010010101100101101 !
#11000
b11001 %
b11 #
b11010 '
b11110 &
b100000110101111001111001 !
#12000
b100 "
b11110 %
b0 $
b110 #
b11011 '
b1100 &
b110110110011011110 !
#13000
b1 "
b10000 %
b0 #
b11000 '
b11011 &
b110001101100010000 !
#14000
b1010 "
b10010 %
b11 #
b11011 '
b11 &
b110110001101110010 !
#15000
b0 "
b11101 %
b100000 $
b10 #
b1000 '
b11011 &
b100000010001101101011101 !
#16000
b100 "
b1001 %
b0 $
b110 #
b110 '
b10010 &
b1101001011001001 !
#17000
b0 "
b10010 %
b100000 $
b1011 '
b10001 &
b100000010111000111010010 !
#18000
b1101 %
b11 #
b1001 '
b100 &
b100000010010010001101101 !
#19000
b10 "
b111 %
b0 #
b11011 '
b1000 &
b100000110110100000000111 !
#20000
b0 "
b100 %
b10 #
b0 '
b10010 &
b100000000001001001000100 !
#21000
b111 %
b111 #
b11100 '
b10000 &
b100000111001000011100111 !
#22000
b10100 %
b100 #
b11001 '
b11100 &
b100000110011110010010100 !
#23000
b11 "
b10010 %
b0 $
b1011 '
b1100 &
b10110110010010010 !
#24000
b0 "
b10110 %
b100000 $
b110 #
b11011 '
b10101 &
b100000110111010111010110 !
#25000
b100 %
b100 #
b10101 '
b11001 &
b100000101011100110000100 !
#26000
b1110 %
b1 #
b11110 '
b11000 &
b100000111101100000101110 !
#27000
b11110 %
b110 #
b11111 '
b11001 &
b100000111111100111011110 !
#28000
b1 "
b111 %
b0 $
b0 #
b1011 '
b10010 &
b10111001000000111 !
#29000
b110 "
b10000 %
b1 #
b10000 '
b11 &
b100000001100110000 !
#30000
b0 "
b111 %
b100000 $
b11 #
b1001 '
b111 &
b100000010010011101100111 !
#31000
b111 "
b10011 %
b0 $
b101 #
b11111 '
b1111 &
b111110111110110011 !
#32000
b11 "
b11100 %
b100 #
b110 '
b11110 &
b1101111010011100 !
#33000
b1001 "
b10101 %
b10 #
b1001 '
b10 &
b10010001001010101 !
#34000
b0 "
b11001 %
b100000 $
b11100 '
b1001 &
b100000111000100101011001 !
#35000
b1000 "
b10100 %
b101 #
b1111 '
b10010 &
b100000011111001010110100 !
#36000
b0 "
b1000 %
b110 #
b1 '
b11001 &
b100000000011100111001000 !
#37000
b11010 %
b100 #
b11111 '
b11011 &
b100000111111101110011010 !
#38000
b101 "
b11111 %
b0 $
b111 #
b1100 '
b10010 &
b11001001011111111 !
#39000
b0 "
b11000 %
b100000 $
b110 #
b10010 '
b1010 &
b100000100100101011011000 !
#40000
b10111 %
b10 #
b11100 '
b10010 &
b100000111001001001010111 !
#41000
b1001 "
b1111 %
b0 $
b1101 '
b10111 &
b11011011101001111 !
#42000
b100 "
b101 %
b110 #
b10010 '
b11011 &
b100101101111000101 !
#43000
b0 "
b10011 %
b100000 $
b10 #
b10101 '
b11001 &
b100000101011100101010011 !
#44000
b100 %
b100 #
b10011 '
b100 &
b100000100110010010000100 !
#45000
b110 "
b1110 %
b0 $
b1 #
b1001 '
b10101 &
b10011010100101110 !
#46000
b101 "
b1 %
b111 #
b10 '
b10110 &
b101011011100001 !
#47000
b111 "
b11001 %
b101 #
b10001 '
b1 &
b100010000110111001 !
#48000
b101 "
b10100 %
b111 #
b11110 '
b11011 &
b111101101111110100 !
#49000
b11 "
b1111 %
b100 #
b11011 '
b10110 &
b110111011010001111 !
#50000
b0 "
b10100 %
b100000 $
b1 #
b1011 '
b1011 &
b100000010110101100110100 !
#51000
b100 "
b110 %
b0 $
b110 #
b11110 '
b10011 &
b111101001111000110 !
#52000
b11 "
b10110 %
b100 #
b1100 '
b10110 &
b11001011010010110 !
#53000
b1001 "
b1101 %
b10 #
b1101 '
b11010 &
b11011101001001101 !
#54000
b0 "
b111 %
b100000 $
b10000 '
b10110 &
b100000100001011001000111 !
#55000
b110 #
b10111 '
b1110 &
b100000101110111011000111 !
#56000
b111 "
b10011 %
b0 $
b101 #
b1100 '
b10101 &
b11001010110110011 !
#57000
b0 "
b110 %
b100000 $
b1 #
b11101 '
b101 &
b100000111010010100100110 !
#58000
b111 "
b11000 %
b0 $
b101 #
b10000 '
b11 &
b100000001110111000 !
#59000
b0 "
b11001 %
b100000 $
b10 #
b100 '
b11111 &
b100000001001111101011001 !
#60000
b1011 %
b111 #
b1100 '
b1110 &
b100000011000111011101011 !
#61000
b10111 %
b11 #
b10 '
b11010 &
b100000000101101001110111 !
#62000
b1010 "
b10010 %
b0 $
b1001 '
b10010 &
b10011001001110010 !
#63000
b1001 "
b1001 %
b10 #
b1010 '
b10101001001001001 !
#64000
b110 "
b10001 %
b1 #
b10000 '
b110 &
b100000011000110001 !
#65000
b1001 "
b11011 %
b10 #
b11010 '
b11101 &
b110101110101011011 !
#66000
b1000 "
b10000 %
b100000 $
b101 #
b10000 '
b1011 &
b100000100000101110110000 !
#67000
b1 "
b10110 %
b0 $
b0 #
b0 '
b1000 &
b100000010110 !
#68000
b10000 %
b1111 '
b10111 &
b11111011100010000 !
#69000
b1010 "
b11000 %
b11 #
b100 '
b1100 &
b1000110001111000 !
#70000
b0 "
b10111 %
b100000 $
b111 #
b10001 &
b100000001001000111110111 !
#71000
b10001 %
b100 #
b0 '
b1111 &
b100000000000111110010001 !
#72000
b1010 "
b111 %
b0 $
b11 #
b1101 '
b11100 &
b11011110001100111 !
#73000
b0 "
b10011 %
b100000 $
b110 #
b10 '
b11000 &
b100000000101100011010011 !
#74000
b11 "
b11100 %
b0 $
b100 #
b1 '
b11 &
b10001110011100 !
#75000
b0 "
b10010 %
b100000 $
b11 #
b11011 '
b11110 &
b100000110111111001110010 !
#76000
b10 %
b111 #
b11110 '
b10011 &
b100000111101001111100010 !
#77000
b1 "
b10111 %
b0 $
b0 #
b1 '
b1101 &
b10110100010111 !
#78000
b0 "
b1000 %
b100000 $
b111 #
b11000 '
b1 &
b100000110000000111101000 !
#79000
b11011 %
b10 #
b11010 '
b11110 &
b100000110101111001011011 !
#80000
b11 "
b100 %
b0 $
b100 #
b10011 '
b11111 &
b100111111110000100 !
#81000
b110 "
b1111 %
b1 #
b1011 '
b0 &
b10110000000101111 !
#82000
b1 "
b10001 %
b0 #
b11111 '
b10101 &
b111111010100010001 !
#83000
b1010 "
b10 %
b11 #
b0 '
b10001 &
b1000101100010 !
#84000
b0 "
b11001 %
b100000 $
b10 #
b10011 '
b110 &
b100000100110011001011001 !
#85000
b10110 %
b1 #
b100 '
b100000001000011000110110 !
#86000
b111 "
b11010 %
b0 $
b101 #
b11000 '
b0 &
b110000000010111010 !
#87000
b1010 "
b10011 %
b11 #
b11001 '
b11001 &
b110011100101110011 !
#88000
b101 "
b1111 %
b111 #
b10101 '
b1001 &
b101010100111101111 !
#89000
b10110 %
b0 '
b1100 &
b110011110110 !
#90000
b0 "
b1001 %
b100000 $
b100 #
b11001 '
b11111 &
b100000110011111110001001 !
#91000
b11100 %
b10 #
b111 '
b111 &
b100000001110011101011100 !
#92000
b1001 %
b11 #
b11010 '
b11100 &
b100000110101110001101001 !
#93000
b111 "
b11010 %
b0 $
b101 #
b10100 '
b1111 &
b101000111110111010 !
#94000
b0 "
b110 %
b100000 $
b10 #
b11111 '
b101 &
b100000111110010101000110 !
#95000
b1010 "
b1011 %
b0 $
b11 #
b11100 '
b100 &
b111000010001101011 !
#96000
b0 "
b1100 %
b100000 $
b1111 '
b11111 &
b100000011111111101101100 !
#97000
b111 "
b11110 %
b0 $
b101 #
b11010 '
b1100 &
b110100110010111110 !
#98000
b1010 "
b11011 %
b11 #
b11000 '
b10111 &
b110001011101111011 !
#99000
b101 "
b1111 %
b111 #
b10010 '
b11111 &
b100101111111101111 !
