ver/ifu.sv

module ifu(
    input logic i_clk,
    input logic i_rst,
    input logic stall_pc,
    input logic pc_update_control,
    input logic [31:0] pc_update_val,
    output logic [31:0] pc,
    output logic [31:0] prev_pc
);

always @(posedge i_clk or negedge i_rst) begin
        if (~i_rst) begin
            prev_pc        <= 32'b0;
        end else begin
            prev_pc        <= pc;
        end
    end
always @(posedge i_clk or negedge i_rst) begin
        if (~i_rst) begin
         pc <= 0;
        end
        else if (stall_pc)begin
         pc<=pc;
        end
        else if (pc_update_control)begin
         pc<= pc_update_val;
        end
        else begin
         pc<=pc+4;
        end
    end
   
`ifndef SUBMODULE_DISABLE_WAVES
   initial
     begin
        $dumpfile("./sim_build/ifu.vcd");
        $dumpvars(0, ifu);
     end
`endif

endmodule

sim_submodules/sim_build/ifu.vcd
$date
	Tue Jul  2 09:43:45 2024
$end
$version
	Icarus Verilog
$end
$timescale
	1ps
$end
$scope module ifu $end
$var wire 1 ! i_clk $end
$var wire 1 " i_rst $end
$var wire 1 # pc_update_control $end
$var wire 32 $ pc_update_val [31:0] $end
$var wire 1 % stall_pc $end
$var reg 32 & pc [31:0] $end
$var reg 32 ' prev_pc [31:0] $end
$upscope $end
$enddefinitions $end
$comment Show the parameter values. $end
$dumpall
$end
#0
$dumpvars
bx '
bx &
0%
b0 $
0#
1"
0!
$end
#5000
1!
#5500
b0 &
b0 '
0"
0!
#6000
1!
#6500
0!
#7000
1"
1!
#7500
0!
#8000
b100 &
1!
#8100
b1110100 $
1%
#8500
0!
#9000
b100 '
1!
#9100
b1111000 $
1#
0%
#9500
0!
#10000
b1111000 &
1!
#10100
b10111100 $
0#
#10500
0!
#11000
b1111100 &
b1111000 '
1!
#11100
b11000000 $
1%
#11500
0!
#12000
b1111100 '
1!
#12100
b11000100 $
0%
#12500
0!
#13000
b10000000 &
1!
#13100
b10100100 $
1#
1%
#13500
0!
#14000
b10000000 '
1!
#14100
b11100000 $
0#
0%
#14500
0!
#15000
b10000100 &
1!
#15100
b10010100 $
1#
1%
#15500
0!
#16000
b10000100 '
1!
#16100
b10100100 $
0#
#16500
0!
#17000
1!
#17100
b11101100 $
1#
#17500
0!
#18000
1!
#18100
b11110100 $
0#
0%
#18500
0!
#19000
b10001000 &
1!
#19100
b11100100 $
1#
1%
#19500
0!
#20000
b10001000 '
1!
#20100
b11111000 $
#20500
0!
#21000
1!
#21100
b11100100 $
0#
#21500
0!
#22000
1!
#22100
b10001000 $
0%
#22500
0!
#23000
b10001100 &
1!
#23100
b100000000 $
1#
1%
#23500
0!
#24000
b10001100 '
1!
#24100
b10010100 $
0#
#24500
0!
#25000
1!
#25100
b10011100 $
1#
0%
#25500
0!
#26000
b10011100 &
1!
#26100
b11011100 $
#26500
0!
#27000
b11011100 &
b10011100 '
1!
#27100
b100011000 $
0#
#27500
0!
#28000
b11011100 '
b11100000 &
1!
#28100
b11100100 $
#28500
0!
#29000
b11100100 &
b11100000 '
1!
#29100
b101100000 $
1%
#29500
0!
#30000
b11100100 '
1!
#30100
b100011000 $
0%
#30500
0!
#31000
b11101000 &
1!
#31100
b101001000 $
1#
1%
#31500
0!
#32000
b11101000 '
1!
#32100
b101100100 $
0%
#32500
0!
#33000
b101100100 &
1!
#33100
b111000100 $
#33500
0!
#34000
b101100100 '
b111000100 &
1!
#34100
b1000011000 $
1%
#34500
0!
#35000
b111000100 '
1!
#35100
0%
#35500
0!
#36000
b1000011000 &
1!
#36100
b1001010000 $
#36500
0!
#37000
b1001010000 &
b1000011000 '
1!
#37100
b1001111000 $
0#
1%
#37500
0!
#38000
b1001010000 '
1!
#38100
b1001101000 $
1#
0%
#38500
0!
#39000
b1001101000 &
1!
#39100
b1010101100 $
#39500
0!
#40000
b1001101000 '
b1010101100 &
1!
#40100
b1011110100 $
0#
1%
#40500
0!
#41000
b1010101100 '
1!
#41100
b1100100000 $
1#
0%
#41500
0!
#42000
b1100100000 &
1!
#42100
b1101111000 $
0#
#42500
0!
#43000
b1100100100 &
b1100100000 '
1!
#43100
b1100110100 $
1#
1%
#43500
0!
#44000
b1100100100 '
1!
#44100
b1101011100 $
0#
#44500
0!
#45000
1!
#45100
b1100101000 $
1#
#45500
0!
#46000
1!
#46100
b1101010000 $
0#
#46500
0!
#47000
1!
#47100
b1101111000 $
0%
#47500
0!
#48000
b1100101000 &
1!
#48100
1%
#48500
0!
#49000
b1100101000 '
1!
#49100
b1100110000 $
1#
#49500
0!
#50000
1!
#50100
b1101100000 $
0#
0%
#50500
0!
#51000
b1100101100 &
1!
#51100
b1110101000 $
1%
#51500
0!
#52000
b1100101100 '
1!
#52100
b1101111100 $
1#
#52500
0!
#53000
1!
#53100
b1100111000 $
0#
#53500
0!
#54000
1!
#54100
b1101110100 $
0%
#54500
0!
#55000
b1100110000 &
1!
#55100
b1110100100 $
1%
#55500
0!
#56000
b1100110000 '
1!
#56100
b1101011100 $
1#
0%
#56500
0!
#57000
b1101011100 &
1!
#57100
b1101110100 $
#57500
0!
#58000
b1101011100 '
b1101110100 &
1!
#58100
b1110000100 $
#58500
0!
#59000
b1110000100 &
b1101110100 '
1!
#59100
b1111100100 $
#59500
0!
#60000
b1110000100 '
b1111100100 &
1!
#60100
b10001000100 $
0#
#60500
0!
#61000
b1111101000 &
b1111100100 '
1!
#61100
b10000100100 $
1#
1%
#61500
0!
#62000
b1111101000 '
1!
#62100
b10000101000 $
0#
#62500
0!
#63000
1!
#63100
b10001011000 $
0%
#63500
0!
#64000
b1111101100 &
1!
#64100
b10000110000 $
1%
#64500
0!
#65000
b1111101100 '
1!
#65100
b10001010000 $
#65500
0!
#66000
1!
#66100
b10000111000 $
1#
#66500
0!
#67000
1!
#67100
b10000000100 $
0#
#67500
0!
#68000
1!
#68100
b10000001100 $
1#
0%
#68500
0!
#69000
b10000001100 &
1!
#69100
b10000011000 $
1%
#69500
0!
#70000
b10000001100 '
1!
#70100
b10001000000 $
0#
#70500
0!
#71000
1!
#71100
b10001110000 $
0%
#71500
0!
#72000
b10000010000 &
1!
#72100
b10001101000 $
#72500
0!
#73000
b10000010100 &
b10000010000 '
1!
#73100
b10001001000 $
1#
#73500
0!
#74000
b10000010100 '
b10001001000 &
1!
#74100
b10010111000 $
1%
#74500
0!
#75000
b10001001000 '
1!
#75100
b10010001000 $
0#
#75500
0!
#76000
1!
#76100
b10010110100 $
1#
#76500
0!
#77000
1!
#77100
b10010011100 $
0#
#77500
0!
#78000
1!
#78100
b10001100100 $
1#
0%
#78500
0!
#79000
b10001100100 &
1!
#79100
b10011010100 $
#79500
0!
#80000
b10001100100 '
b10011010100 &
1!
#80100
b10011101100 $
0#
1%
#80500
0!
#81000
b10011010100 '
1!
#81100
b10100101000 $
0%
#81500
0!
#82000
b10011011000 &
1!
#82100
b10101010000 $
1#
#82500
0!
#83000
b10101010000 &
b10011011000 '
1!
#83100
b10101110000 $
1%
#83500
0!
#84000
b10101010000 '
1!
#84100
b10110001100 $
#84500
0!
#85000
1!
#85100
b10110001000 $
0#
0%
#85500
0!
#86000
b10101010100 &
1!
#86100
b10101011100 $
1#
1%
#86500
0!
#87000
b10101010100 '
1!
#87100
b10110101000 $
0#
#87500
0!
#88000
1!
#88100
b10110010000 $
1#
#88500
0!
#89000
1!
#89100
b10110000000 $
0#
#89500
0!
#90000
1!
#90100
b10110111000 $
1#
#90500
0!
#91000
1!
#91100
b10110111100 $
0%
#91500
0!
#92000
b10110111100 &
1!
#92100
b10111011000 $
0#
1%
#92500
0!
#93000
b10110111100 '
1!
#93100
b10111010000 $
#93500
0!
#94000
1!
#94100
b10111111100 $
1#
#94500
0!
#95000
1!
#95100
b11000111000 $
0%
#95500
0!
#96000
b11000111000 &
1!
#96100
b11001000000 $
0#
1%
#96500
0!
#97000
b11000111000 '
1!
#97100
b11001101000 $
1#
#97500
0!
#98000
1!
#98100
b11001100000 $
0%
#98500
0!
#99000
b11001100000 &
1!
#99100
b11011000100 $
0#
1%
#99500
0!
#100000
b11001100000 '
1!
#100100
0%
#100500
0!
#101000
b11001100100 &
1!
#101100
b11001101000 $
1%
#101500
0!
#102000
b11001100100 '
1!
#102100
b11010111100 $
#102500
0!
#103000
1!
#103100
b11010011100 $
0%
#103500
0!
#104000
b11001101000 &
1!
#104100
b11011000100 $
1#
1%
#104500
0!
#105000
b11001101000 '
1!
#105100
b11011001000 $
0#
0%
#105500
0!
#106000
b11001101100 &
1!
#106100
b11010000000 $
1#
#106500
0!
#107000
b11010000000 &
b11001101100 '
1!
