ver/jump.sv

`ifndef FILE_INCL
    `include "processor_defines.sv"
`endif

module jump(
    input logic i_clk,
    input logic i_rst,
    input logic [31:0] pc,
    input logic [31:0] imm,
    input logic [31:0] rs1_val,
    input logic [1:0] jump_control,
    output logic rd_write_control,
    output logic [31:0] rd_write_val,
    output logic pc_update_control,
    output logic [31:0] pc_update_val,
    output logic ignore_curr_inst
);
always_comb begin
    case(jump_control)
    `JMP_NOP: begin
        rd_write_control=0;
        rd_write_val=0;
        pc_update_control=0;
        pc_update_val=0;
    end
    `JAL: begin
        rd_write_control=1;
        rd_write_val=pc+4;
        pc_update_control=1;
        pc_update_val=pc+imm;
    end
    `JALR: begin
        rd_write_control=1;
        rd_write_val=pc+4;
        pc_update_control=1;
        pc_update_val=rs1_val+imm;
    end
    default: begin
        rd_write_control=0;
        rd_write_val=0;
        pc_update_control=0;
        pc_update_val=0;
    end
    
    endcase
end
always_ff @(posedge i_clk or negedge i_rst) begin
    if (!i_rst) begin
        ignore_curr_inst <= 0;
    end else begin
        ignore_curr_inst <= pc_update_control;
    end
end

`ifndef SUBMODULE_DISABLE_WAVES
   initial
     begin
        $dumpfile("./sim_build/jump.vcd");
        $dumpvars(0, jump);
     end
 `endif

endmodule

sim_submodules/sim_build/jump.vcd
$date
	Wed Jul  3 13:51:21 2024
$end
$version
	Icarus Verilog
$end
$timescale
	1ps
$end
$scope module jump $end
$var wire 1 ! i_clk $end
$var wire 1 " i_rst $end
$var wire 32 # imm [31:0] $end
$var wire 2 $ jump_control [1:0] $end
$var wire 32 % pc [31:0] $end
$var wire 32 & rs1_val [31:0] $end
$var reg 1 ' ignore_curr_inst $end
$var reg 1 ( pc_update_control $end
$var reg 32 ) pc_update_val [31:0] $end
$var reg 1 * rd_write_control $end
$var reg 32 + rd_write_val [31:0] $end
$upscope $end
$enddefinitions $end
$comment Show the parameter values. $end
$dumpall
$end
#0
$dumpvars
b0 +
0*
b0 )
0(
x'
b0 &
b0 %
b0 $
b0 #
1"
0!
$end
#5000
0'
1!
#5500
0"
0!
#6000
1!
#6500
0!
#7000
1"
1!
#7500
0!
#8000
1!
#8100
b101001011101 #
b10010011000111011111001011010 &
b110110010100111111101100000101 %
#8500
0!
#9000
1!
#9100
b11110110110010101110111100100 )
1(
b11110110110010101011000100111 +
1*
b1 $
b11111000001 #
b110100101001010001100010101011 &
b11110110110010101011000100011 %
#9500
0!
#10000
b0 )
0(
b0 +
0*
b0 $
b0 #
b0 &
b11110110110010101011000100111 %
1'
1!
#10500
0!
#11000
0'
1!
#11100
b111101111101 #
b1111010100011101010110111010 &
b10011010010110010011101000100 %
#11500
0!
#12000
1!
#12100
b111101100001110111101000100001 )
1(
b110110000011101110111111001 +
1*
b10 $
b11000001 #
b111101100001110111100101100000 &
b110110000011101110111110101 %
#12500
0!
#13000
b0 )
0(
b0 +
0*
b0 $
b0 #
b0 &
b110110000011101110111111001 %
1'
1!
#13500
0!
#14000
0'
1!
#14100
b100011011000 #
b1110001110000001010011110011 &
b10110010100010001101010001101 %
#14500
0!
#15000
1!
#15100
b100100111111111110000100111100 )
1(
b101001011111111010011011101010 +
1*
b10 $
b10110010000 #
b100100111111111101101110101100 &
b101001011111111010011011100110 %
#15500
0!
#16000
b0 )
0(
b0 +
0*
b0 $
b0 #
b0 &
b101001011111111010011011101010 %
1'
1!
#16500
0!
#17000
0'
1!
#17100
b10001010100010101001010110000 )
1(
b100101001100110100010011 +
1*
b10 $
b111010100010 #
b10001010100010100010000001110 &
b100101001100110100001111 %
#17500
0!
#18000
b0 )
0(
b0 +
0*
b0 $
b0 #
b0 &
b100101001100110100010011 %
1'
1!
#18500
0!
#19000
0'
1!
#19100
b111000011100111101110101110010 )
1(
b111000011100111101001101010110 +
1*
b1 $
b101000100000 #
b100100100000010111010001010110 &
b111000011100111101001101010010 %
#19500
0!
#20000
b0 )
0(
b0 +
0*
b0 $
b0 #
b0 &
b111000011100111101001101010110 %
1'
1!
#20500
0!
#21000
0'
1!
#21100
b100001111101100101011011101011 )
1(
b100001111101100101010101000010 +
1*
b1 $
b110101101 #
b11101001000010010011110110100 &
b100001111101100101010100111110 %
#21500
0!
#22000
b0 )
0(
b0 +
0*
b0 $
b0 #
b0 &
b100001111101100101010101000010 %
1'
1!
#22500
0!
#23000
0'
1!
#23100
b11111000100100000101000101100 )
1(
b11111000100100000001100110001 +
1*
b1 $
b11011111111 #
b11110010001100100101101010110 &
b11111000100100000001100101101 %
#23500
0!
#24000
b0 )
0(
b0 +
0*
b0 $
b0 #
b0 &
b11111000100100000001100110001 %
1'
1!
#24500
0!
#25000
0'
1!
#25100
b110110101001110110000001000001 )
1(
b110110101001110101100001111011 +
1*
b1 $
b11111001010 #
b111110101111111001011110001011 &
b110110101001110101100001110111 %
#25500
0!
#26000
b0 )
0(
b0 +
0*
b0 $
b0 #
b0 &
b110110101001110101100001111011 %
1'
1!
#26500
0!
#27000
0'
1!
#27100
b10111001010010010101111001010 )
1(
b111111110111111101100111100100 +
1*
b10 $
b111010011010 #
b10111001010010001110100110000 &
b111111110111111101100111100000 %
#27500
0!
#28000
b0 )
0(
b0 +
0*
b0 $
b0 #
b0 &
b111111110111111101100111100100 %
1'
1!
#28500
0!
#29000
0'
1!
#29100
b110111101110 #
b1100111101011101101001001111 &
b100101001000000100100100100110 %
#29500
0!
#30000
1!
#30100
b101000010011000101010101110000 )
1(
b101000010011000100110010110001 +
1*
b1 $
b100011000011 #
b101100110010101101101111001010 &
b101000010011000100110010101101 %
#30500
0!
#31000
b0 )
0(
b0 +
0*
b0 $
b0 #
b0 &
b101000010011000100110010110001 %
1'
1!
#31500
0!
#32000
0'
1!
#32100
b10110111100001110101101100110 )
1(
b10110111100001110011001111001 +
1*
b1 $
b10011110001 #
b110011111011011011110010011011 &
b10110111100001110011001110101 %
#32500
0!
#33000
b0 )
0(
b0 +
0*
b0 $
b0 #
b0 &
b10110111100001110011001111001 %
1'
1!
#33500
0!
#34000
0'
1!
#34100
b101111010101101000010101011110 )
1(
b10000101100110100100000010110 +
1*
b10 $
b110101001 #
b101111010101101000001110110101 &
b10000101100110100100000010010 %
#34500
0!
#35000
b0 )
0(
b0 +
0*
b0 $
b0 #
b0 &
b10000101100110100100000010110 %
1'
1!
#35500
0!
#36000
0'
1!
#36100
b110000111010 #
b110001001000000011100000101000 &
b101110111011000110101101101010 %
#36500
0!
#37000
1!
#37100
b100001101101100000011100110010 )
1(
b100001101101011111100011111101 +
1*
b1 $
b111000111001 #
b11101100111101001110001001111 &
b100001101101011111100011111001 %
#37500
0!
#38000
b0 )
0(
b0 +
0*
b0 $
b0 #
b0 &
b100001101101011111100011111101 %
1'
1!
#38500
0!
#39000
0'
1!
#39100
b1011100110010000111010011011 )
1(
b1011100110010000001100010011 +
1*
b1 $
b101110001100 #
b10110001111110010110011000110 &
b1011100110010000001100001111 %
#39500
0!
#40000
b0 )
0(
b0 +
0*
b0 $
b0 #
b0 &
b1011100110010000001100010011 %
1'
1!
#40500
0!
#41000
0'
1!
#41100
b111100000111101001110001001111 )
1(
b111100000111101001001111101001 +
1*
b1 $
b100001101010 #
b101001011010000101011111011111 &
b111100000111101001001111100101 %
#41500
0!
#42000
b0 )
0(
b0 +
0*
b0 $
b0 #
b0 &
b111100000111101001001111101001 %
1'
1!
#42500
0!
#43000
0'
1!
#43100
b111101000000 #
b111000100110011110111110111000 &
b111101101011101010010001100011 %
#43500
0!
#44000
1!
#44100
b10000101010 #
b110111100100110101001101010110 &
b1111100001110101001101001001 %
#44500
0!
#45000
1!
#45100
b111101111110101011101100110001 )
1(
b111101111110101011001110000001 +
1*
b1 $
b11110110100 #
b1010100110000110101011111010 &
b111101111110101011001101111101 %
#45500
0!
#46000
b0 )
0(
b0 +
0*
b0 $
b0 #
b0 &
b111101111110101011001110000001 %
1'
1!
#46500
0!
#47000
0'
1!
#47100
b10000011100000000001100110100 )
1(
b10101100011100101111001111110 +
1*
b10 $
b10001100100 #
b10000011011111111111011010000 &
b10101100011100101111001111010 %
#47500
0!
#48000
b0 )
0(
b0 +
0*
b0 $
b0 #
b0 &
b10101100011100101111001111110 %
1'
1!
#48500
0!
#49000
0'
1!
#49100
b111011001011 #
b10010001111000101111111111101 &
b100111100101110110101110110101 %
#49500
0!
#50000
1!
#50100
b11011100001100101010111101001 )
1(
b110011100000010001001110110100 +
1*
b10 $
b11011101110 #
b11011100001100100111011111011 &
b110011100000010001001110110000 %
#50500
0!
#51000
b0 )
0(
b0 +
0*
b0 $
b0 #
b0 &
b110011100000010001001110110100 %
1'
1!
#51500
0!
#52000
0'
1!
#52100
b110000001111110101111000011 )
1(
b101001001001000001100001001110 +
1*
b10 $
b110001011001 #
b110000001111101111101101010 &
b101001001001000001100001001010 %
#52500
0!
#53000
b0 )
0(
b0 +
0*
b0 $
b0 #
b0 &
b101001001001000001100001001110 %
1'
1!
#53500
0!
#54000
0'
1!
#54100
b11000101001100011111100100100 )
1(
b11000101001100011001011111110 +
1*
b1 $
b110000101010 #
b10011110100010001011101101101 &
b11000101001100011001011111010 %
#54500
0!
#55000
b0 )
0(
b0 +
0*
b0 $
b0 #
b0 &
b11000101001100011001011111110 %
1'
1!
#55500
0!
#56000
0'
1!
#56100
b111011111111001101110000101100 )
1(
b111100011010110011011010100111 +
1*
b10 $
b10101011110 #
b111011111111001101011011001110 &
b111100011010110011011010100011 %
#56500
0!
#57000
b0 )
0(
b0 +
0*
b0 $
b0 #
b0 &
b111100011010110011011010100111 %
1'
1!
#57500
0!
#58000
0'
1!
#58100
b111001110011111000000111000110 )
1(
b10001000111110000111110110111 +
1*
b10 $
b111010100001 #
b111001110011110111001100100101 &
b10001000111110000111110110011 %
#58500
0!
#59000
b0 )
0(
b0 +
0*
b0 $
b0 #
b0 &
b10001000111110000111110110111 %
1'
1!
#59500
0!
#60000
0'
1!
#60100
b1011110011001111111000110110 )
1(
b110010000111111011010010111001 +
1*
b10 $
b11001111110 #
b1011110011001111011110111000 &
b110010000111111011010010110101 %
#60500
0!
#61000
b0 )
0(
b0 +
0*
b0 $
b0 #
b0 &
b110010000111111011010010111001 %
1'
1!
#61500
0!
#62000
0'
1!
#62100
b10001000101000110100000001111 )
1(
b10001000101000110000100010100 +
1*
b1 $
b11011111111 #
b111010010100101011010111001000 &
b10001000101000110000100010000 %
#62500
0!
#63000
b0 )
0(
b0 +
0*
b0 $
b0 #
b0 &
b10001000101000110000100010100 %
1'
1!
#63500
0!
#64000
0'
1!
#64100
b111100010101 #
b1110011000010011100001011111 &
b111100110100111010010110110010 %
#64500
0!
#65000
1!
#65100
b111000100 #
b110110001100101110100100110111 &
b10010101011100010010001000100 %
#65500
0!
#66000
1!
#66100
b1110110010 #
b100101011001101011001000110111 &
b11001011111010100000001110000 %
#66500
0!
#67000
1!
#67100
b1101100101 #
b101100001101110111010110110001 &
b100101000111011111001000110001 %
#67500
0!
#68000
1!
#68100
b11101100000100010011001001100 )
1(
b110101110011011100001101011100 +
1*
b10 $
b101000011011 #
b11101100000100001110000110001 &
b110101110011011100001101011000 %
#68500
0!
#69000
b0 )
0(
b0 +
0*
b0 $
b0 #
b0 &
b110101110011011100001101011100 %
1'
1!
#69500
0!
#70000
0'
1!
#70100
b100110001100 #
b101011000111110000001001010111 &
b101010100100101010001001000111 %
#70500
0!
#71000
1!
#71100
b101111111001100000000011110001 )
1(
b101111111001011111010110011100 +
1*
b1 $
b101101011001 #
b1001101001101100111010001000 &
b101111111001011111010110011000 %
#71500
0!
#72000
b0 )
0(
b0 +
0*
b0 $
b0 #
b0 &
b101111111001011111010110011100 %
1'
1!
#72500
0!
#73000
0'
1!
#73100
b101011111010 #
b11101111000111110000101100001 &
b11001110100101101010011110010 %
#73500
0!
#74000
1!
#74100
b1101101000101000011010101110 )
1(
b1101101000100111111010001110 +
1*
b1 $
b100000100100 #
b101101100000010010110001000001 &
b1101101000100111111010001010 %
#74500
0!
#75000
b0 )
0(
b0 +
0*
b0 $
b0 #
b0 &
b1101101000100111111010001110 %
1'
1!
#75500
0!
#76000
0'
1!
#76100
b101001100110 #
b10010011101111011110110000000 &
b111110100110100110000001 %
#76500
0!
#77000
1!
#77100
b110001001111111011001101110111 )
1(
b110100010110001000110100010110 +
1*
b10 $
b110001111100 #
b110001001111111010011011111011 &
b110100010110001000110100010010 %
#77500
0!
#78000
b0 )
0(
b0 +
0*
b0 $
b0 #
b0 &
b110100010110001000110100010110 %
1'
1!
#78500
0!
#79000
0'
1!
#79100
b100001111000011000101000000010 )
1(
b10010100101110110111110011100 +
1*
b10 $
b101111001111 #
b100001111000010111111000110011 &
b10010100101110110111110011000 %
#79500
0!
#80000
b0 )
0(
b0 +
0*
b0 $
b0 #
b0 &
b10010100101110110111110011100 %
1'
1!
#80500
0!
#81000
0'
1!
#81100
b10011111100001010010000110111 )
1(
b101011000010100110111001000001 +
1*
b10 $
b110111110 #
b10011111100001010001001111001 &
b101011000010100110111000111101 %
#81500
0!
#82000
b0 )
0(
b0 +
0*
b0 $
b0 #
b0 &
b101011000010100110111001000001 %
1'
1!
#82500
0!
#83000
0'
1!
#83100
b110100000010 #
b101101011110111010000001000010 &
b111101000110010101110011111 %
#83500
0!
#84000
1!
#84100
b11010010101100110101001010001 )
1(
b11110010000111100001110100110 +
1*
b10 $
b100101101110 #
b11010010101100110000011100011 &
b11110010000111100001110100010 %
#84500
0!
#85000
b0 )
0(
b0 +
0*
b0 $
b0 #
b0 &
b11110010000111100001110100110 %
1'
1!
#85500
0!
#86000
0'
1!
#86100
b111001110001110011010010001110 )
1(
b10101001110111101100110111010 +
1*
b10 $
b1011100 #
b111001110001110011010000110010 &
b10101001110111101100110110110 %
#86500
0!
#87000
b0 )
0(
b0 +
0*
b0 $
b0 #
b0 &
b10101001110111101100110111010 %
1'
1!
#87500
0!
#88000
0'
1!
#88100
b101000111100 #
b100001011010111101001101011011 &
b10101111011100000011010000010 %
#88500
0!
#89000
1!
#89100
b100101111110111111111011010100 )
1(
b10001100111010111011001110100 +
1*
b10 $
b10110111000 #
b100101111110111111100100011100 &
b10001100111010111011001110000 %
#89500
0!
#90000
b0 )
0(
b0 +
0*
b0 $
b0 #
b0 &
b10001100111010111011001110100 %
1'
1!
#90500
0!
#91000
0'
1!
#91100
b100110100101001001110100011101 )
1(
b100110100101001000111101000010 +
1*
b1 $
b110111011111 #
b100001111011110111100000110101 &
b100110100101001000111100111110 %
#91500
0!
#92000
b0 )
0(
b0 +
0*
b0 $
b0 #
b0 &
b100110100101001000111101000010 %
1'
1!
#92500
0!
#93000
0'
1!
#93100
b100100010000101110001011 )
1(
b110011000100110001111110011011 +
1*
b10 $
b110100111 #
b100100010000100111100100 &
b110011000100110001111110010111 %
#93500
0!
#94000
b0 )
0(
b0 +
0*
b0 $
b0 #
b0 &
b110011000100110001111110011011 %
1'
1!
#94500
0!
#95000
0'
1!
#95100
b101010110111110111011101110010 )
1(
b101111110100010000001000111001 +
1*
b10 $
b111010010110 #
b101010110111110110100011011100 &
b101111110100010000001000110101 %
#95500
0!
#96000
b0 )
0(
b0 +
0*
b0 $
b0 #
b0 &
b101111110100010000001000111001 %
1'
1!
#96500
0!
#97000
0'
1!
#97100
b100101100101 #
b100000110000010011101100100010 &
b11101010011001111111101001011 %
#97500
0!
#98000
1!
#98100
b10101101010011000001101101001 )
1(
b10101101010010111110110001111 +
1*
b1 $
b10111011110 #
b111101001011000001110100100111 &
b10101101010010111110110001011 %
#98500
0!
#99000
b0 )
0(
b0 +
0*
b0 $
b0 #
b0 &
b10101101010010111110110001111 %
1'
1!
#99500
0!
#100000
0'
1!
#100100
b10001000100100100010011001000 )
1(
b10001000100100100010010011011 +
1*
b1 $
b110001 #
b101001010111100100011101011111 &
b10001000100100100010010010111 %
#100500
0!
#101000
b0 )
0(
b0 +
0*
b0 $
b0 #
b0 &
b10001000100100100010010011011 %
1'
1!
#101500
0!
#102000
0'
1!
#102100
b110101011001 #
b1111001111110010011010100000 &
b10110110001100000010111100110 %
#102500
0!
#103000
1!
#103100
b110011001111101100000100000 )
1(
b110011001111101000101000111 +
1*
b1 $
b11011011101 #
b111001101111110011000001111011 &
b110011001111101000101000011 %
#103500
0!
#104000
b0 )
0(
b0 +
0*
b0 $
b0 #
b0 &
b110011001111101000101000111 %
1'
1!
#104500
0!
#105000
0'
1!
#105100
b100011110000101111001000111100 )
1(
b100011110000101110001011111110 +
1*
b1 $
b111101000010 #
b101111111100000101100100101110 &
b100011110000101110001011111010 %
#105500
0!
#106000
b0 )
0(
b0 +
0*
b0 $
b0 #
b0 &
b100011110000101110001011111110 %
1'
1!
#106500
0!
#107000
0'
1!
#107100
b11110000000 #
b10101111010000011100011010010 &
b1000111101100000100011111110 %
#107500
0!
#108000
1!
#108100
b110101101110 #
b110010011000100001101010000110 &
b11101001000001001100111010010 %
#108500
0!
#109000
1!
#109100
b1111011101 #
b101110010010011110100011011 &
b10011011110001100110010101100 %
#109500
0!
#110000
1!
#110100
b110111111110000001101001010010 )
1(
b1111001101011000011000110101 +
1*
b10 $
b111000101110 #
b110111111110000000110000100100 &
b1111001101011000011000110001 %
#110500
0!
#111000
b0 )
0(
b0 +
0*
b0 $
b0 #
b0 &
b1111001101011000011000110101 %
1'
1!
#111500
0!
#112000
0'
1!
#112100
b101111001001100101100111101011 )
1(
b101111001001100100101110000011 +
1*
b1 $
b111001101100 #
b1010011111011110011011011000 &
b101111001001100100101101111111 %
#112500
0!
#113000
b0 )
0(
b0 +
0*
b0 $
b0 #
b0 &
b101111001001100100101110000011 %
1'
1!
#113500
0!
#114000
0'
1!
#114100
b101111101 #
b11100000000011001000100111100 &
b100100000001000000110001000111 %
#114500
0!
#115000
1!
#115100
b101010001110110111101100001001 )
1(
b101010001110110110101111000010 +
1*
b1 $
b111101001011 #
b111110001101110000011110001110 &
b101010001110110110101110111110 %
#115500
0!
#116000
b0 )
0(
b0 +
0*
b0 $
b0 #
b0 &
b101010001110110110101111000010 %
1'
1!
#116500
0!
#117000
0'
1!
#117100
b100100100101 #
b11110110011110101010000001010 &
b10000111000100110101000001101 %
#117500
0!
#118000
1!
#118100
b11001110111010100010010101101 )
1(
b11001110111010011010101001101 +
1*
b1 $
b111101100100 #
b10000110101000111000000011000 &
b11001110111010011010101001001 %
#118500
0!
#119000
b0 )
0(
b0 +
0*
b0 $
b0 #
b0 &
b11001110111010011010101001101 %
1'
1!
#119500
0!
#120000
0'
1!
#120100
b111000100101 #
b111110011110110100011000000110 &
b101111110011001100111100010001 %
#120500
0!
#121000
1!
#121100
b111000101010 #
b101000001001001010100 &
b10000111001010001010000010100 %
#121500
0!
#122000
1!
#122100
b1001010001010000001110000001 )
1(
b1001010001001111111111111010 +
1*
b1 $
b1110001011 #
b110101100000010111010011001111 &
b1001010001001111111111110110 %
#122500
0!
#123000
b0 )
0(
b0 +
0*
b0 $
b0 #
b0 &
b1001010001001111111111111010 %
1'
1!
#123500
0!
#124000
0'
1!
#124100
b110010001010000101011111100 )
1(
b110010001010000011101000101 +
1*
b1 $
b1110111011 #
b101010100110101100010001100000 &
b110010001010000011101000001 %
#124500
0!
#125000
b0 )
0(
b0 +
0*
b0 $
b0 #
b0 &
b110010001010000011101000101 %
1'
1!
#125500
0!
#126000
0'
1!
#126100
b1001001100 #
b10001111101101011111110010011 &
b111011010001010000001011110110 %
#126500
0!
#127000
1!
#127100
b10100101010 #
b111100110111001000100111100011 &
b110111100001100100101010 %
#127500
0!
#128000
1!
#128100
b11110110000100110111100011101 )
1(
b10001110100100111001100010101 +
1*
b10 $
b11101010 #
b11110110000100110111000110011 &
b10001110100100111001100010001 %
#128500
0!
#129000
b0 )
0(
b0 +
0*
b0 $
b0 #
b0 &
b10001110100100111001100010101 %
1'
1!
#129500
0!
#130000
0'
1!
#130100
b1101100100010010000110110111 )
1(
b1101100100010001101100010101 +
1*
b1 $
b11010100110 #
b11001101101010011010100101010 &
b1101100100010001101100010001 %
#130500
0!
#131000
b0 )
0(
b0 +
0*
b0 $
b0 #
b0 &
b1101100100010001101100010101 %
1'
1!
#131500
0!
#132000
0'
1!
#132100
b11011101000110110011000111011 )
1(
b100001100100101001111000010011 +
1*
b10 $
b100001111001 #
b11011101000110101110111000010 &
b100001100100101001111000001111 %
#132500
0!
#133000
b0 )
0(
b0 +
0*
b0 $
b0 #
b0 &
b100001100100101001111000010011 %
1'
1!
#133500
0!
#134000
0'
1!
#134100
b11100100111100100000101110101 )
1(
b11100100111100011001100001010 +
1*
b1 $
b111001101111 #
b110010110011011100111010100001 &
b11100100111100011001100000110 %
#134500
0!
#135000
b0 )
0(
b0 +
0*
b0 $
b0 #
b0 &
b11100100111100011001100001010 %
1'
1!
#135500
0!
#136000
0'
1!
#136100
b111110110011011111011110100100 )
1(
b100111111001100110010111101001 +
1*
b10 $
b101100101101 #
b111110110011011110110001110111 &
b100111111001100110010111100101 %
#136500
0!
#137000
b0 )
0(
b0 +
0*
b0 $
b0 #
b0 &
b100111111001100110010111101001 %
1'
1!
#137500
0!
#138000
0'
1!
#138100
b1000110100001100011000100111 )
1(
b100010111100000100000101110111 +
1*
b10 $
b1010000100 #
b1000110100001100001110100011 &
b100010111100000100000101110011 %
#138500
0!
#139000
b0 )
0(
b0 +
0*
b0 $
b0 #
b0 &
b100010111100000100000101110111 %
1'
1!
#139500
0!
#140000
0'
1!
#140100
b100101101011001001100000000101 )
1(
b101111010101111100011010011110 +
1*
b10 $
b101111111010 #
b100101101011001000110000001011 &
b101111010101111100011010011010 %
#140500
0!
#141000
b0 )
0(
b0 +
0*
b0 $
b0 #
b0 &
b101111010101111100011010011110 %
1'
1!
#141500
0!
#142000
0'
1!
#142100
b100100101101 #
b1001010111001010001000011100 &
b111100000110010010010100100110 %
#142500
0!
#143000
1!
#143100
b100110010000011000011001101011 )
1(
b100110010000010111101111001111 +
1*
b1 $
b101010100000 #
b111001001110001110000011000100 &
b100110010000010111101111001011 %
#143500
0!
#144000
b0 )
0(
b0 +
0*
b0 $
b0 #
b0 &
b100110010000010111101111001111 %
1'
1!
#144500
0!
#145000
0'
1!
#145100
b111101100000110010010011011010 )
1(
b101101000000000010100010110 +
1*
b10 $
b100010110000 #
b111101100000110001110000101010 &
b101101000000000010100010010 %
#145500
0!
#146000
b0 )
0(
b0 +
0*
b0 $
b0 #
b0 &
b101101000000000010100010110 %
1'
1!
#146500
0!
#147000
0'
1!
#147100
b10011000010101010101000001100 )
1(
b10011000010101010011110100000 +
1*
b1 $
b1001110000 #
b111111100100101111100000110110 &
b10011000010101010011110011100 %
#147500
0!
#148000
b0 )
0(
b0 +
0*
b0 $
b0 #
b0 &
b10011000010101010011110100000 %
1'
1!
#148500
0!
#149000
0'
1!
#149100
b111011101101000011110000110100 )
1(
b111011101101000011011111011111 +
1*
b1 $
b10001011001 #
b10111011010111101001110101110 &
b111011101101000011011111011011 %
#149500
0!
#150000
b0 )
0(
b0 +
0*
b0 $
b0 #
b0 &
b111011101101000011011111011111 %
1'
1!
#150500
0!
#151000
0'
1!
#151100
b101101111111000110100000111110 )
1(
b1101011001111001100011011001 +
1*
b10 $
b11101 #
b101101111111000110100000100001 &
b1101011001111001100011010101 %
#151500
0!
#152000
b0 )
0(
b0 +
0*
b0 $
b0 #
b0 &
b1101011001111001100011011001 %
1'
1!
#152500
0!
#153000
0'
1!
#153100
b111111001011111100110100110010 )
1(
b111111001011111100101001111010 +
1*
b1 $
b1010111100 #
b10110011110010111000100010011 &
b111111001011111100101001110110 %
#153500
0!
#154000
b0 )
0(
b0 +
0*
b0 $
b0 #
b0 &
b111111001011111100101001111010 %
1'
1!
#154500
0!
#155000
0'
1!
#155100
b100001001010001001001100110011 )
1(
b100001001010001000111001011101 +
1*
b1 $
b10011011010 #
b100011001000100010111110111110 &
b100001001010001000111001011001 %
#155500
0!
#156000
b0 )
0(
b0 +
0*
b0 $
b0 #
b0 &
b100001001010001000111001011101 %
1'
1!
#156500
0!
#157000
0'
1!
#157100
b11101 #
b100010101111010010010010010100 &
b110101101110010100101101011 %
#157500
0!
#158000
1!
#158100
b111011110111 #
b1101011000110001000100010110 &
b1100110011110001001100011101 %
#158500
0!
#159000
1!
#159100
b111111001010 #
b110101010111111101101110011101 &
b10011101111001001000000011110 %
#159500
0!
#160000
1!
#160100
b1000111111100001101111101100 )
1(
b111001011110000000001001100100 +
1*
b10 $
b10101110011 #
b1000111111100001011001111001 &
b111001011110000000001001100000 %
#160500
0!
#161000
b0 )
0(
b0 +
0*
b0 $
b0 #
b0 &
b111001011110000000001001100100 %
1'
1!
#161500
0!
#162000
0'
1!
#162100
b11011101111100011010001000111 )
1(
b11011101111100010110101010000 +
1*
b1 $
b11011111011 #
b111000111101110010011011101101 &
b11011101111100010110101001100 %
#162500
0!
#163000
b0 )
0(
b0 +
0*
b0 $
b0 #
b0 &
b11011101111100010110101010000 %
1'
1!
#163500
0!
#164000
0'
1!
#164100
b11111111111101001100100111110 )
1(
b11111111111101001000011110100 +
1*
b1 $
b100001001110 #
b110011101001011111101101001011 &
b11111111111101001000011110000 %
#164500
0!
#165000
b0 )
0(
b0 +
0*
b0 $
b0 #
b0 &
b11111111111101001000011110100 %
1'
1!
#165500
0!
#166000
0'
1!
#166100
b111000101000 #
b111001001010111011000100001 &
b10001100011010001001001001110 %
#166500
0!
#167000
1!
#167100
b100100010110111111011000000011 )
1(
b100100010110111111001001111011 +
1*
b1 $
b1110001100 #
b10101111001100011010111111110 &
b100100010110111111001001110111 %
#167500
0!
#168000
b0 )
0(
b0 +
0*
b0 $
b0 #
b0 &
b100100010110111111001001111011 %
1'
1!
#168500
0!
#169000
0'
1!
#169100
b101011010011100011011010010100 )
1(
b101011010011100011001101001000 +
1*
b1 $
b1101010000 #
b1011011010001100111010111001 &
b101011010011100011001101000100 %
#169500
0!
#170000
b0 )
0(
b0 +
0*
b0 $
b0 #
b0 &
b101011010011100011001101001000 %
1'
1!
#170500
0!
#171000
0'
1!
#171100
b101111100101 #
b1011111101000011010101010011 &
b10101100110001110110101010000 %
