ver/load.sv
`ifndef FILE_INCL
    `include "processor_defines.sv"
`endif

module load(
    input logic i_clk,
    input logic i_rst,
    input logic [31:0] rs1_val,
    input logic [31:0] imm,
    input logic [31:0] mem_data,
    input logic [4:0] rd_in,
    input logic [2:0] load_control,
    output logic stall_pc,
    output logic ignore_curr_inst,
    output logic rd_write_control,
    output logic [4:0] rd_out,
    output logic [31:0] rd_write_val,
    output logic mem_rw_mode,
    output logic [31:0] mem_addr
);

`ifndef SUBMODULE_DISABLE_WAVES
   initial begin
       $dumpfile("./sim_build/load.vcd");
       $dumpvars(0, load);
   end
`endif

logic [31:0] mem_write_val;
//logic [4:0] temp_rd;
logic [2:0] load_control_reg;
logic state, next_state;
logic [1:0]mem_addr_lsb;

assign mem_rw_mode = 1'b1;

always@(*) begin
    case (state) 
        0:begin 
        ignore_curr_inst = 1'b0;
        rd_write_control = 1'b0;
        rd_write_val = 32'b0;
        if (load_control!=`LD_NOP) begin
        next_state=1;
        stall_pc = 1'b1;
        mem_addr = rs1_val + imm;
        end
        else begin
            next_state=0;
            stall_pc = 1'b0;
            mem_addr = 32'h0;
        end 
       
       
        end

        1:begin
        next_state=0;
        stall_pc = 1'b0;
        ignore_curr_inst = 1'b1;
        rd_write_control = 1'b1;
        rd_write_val = mem_write_val; 
        mem_addr = 32'h0;
    end
    endcase

    
    
end

always_ff @(posedge i_clk or negedge i_rst) begin
    if (!i_rst) begin
        state <= 0;
    end else begin
        state <= next_state;
    end
end
always_ff @(posedge i_clk or negedge i_rst) begin
    load_control_reg<=load_control;
    if (next_state)begin
        rd_out<=rd_in;
        mem_addr_lsb<=mem_addr[1:0];
    end
    else begin
        rd_out<=5'd0;
        mem_addr_lsb<=2'b0;
    end

end

always_comb begin
    mem_write_val=32'h0;
    case(load_control_reg) 
       
       `LB : begin
        case(mem_addr_lsb)
        2'h0: mem_write_val={{24{mem_data[7]}}, mem_data[7:0]};
        2'h1: mem_write_val={{24{mem_data[15]}}, mem_data[15:8]};
        2'h2: mem_write_val={{24{mem_data[23]}}, mem_data[23:16]};
        2'h3: mem_write_val={{24{mem_data[31]}}, mem_data[31:24]};
        endcase
       end
       `LW : mem_write_val = mem_data;
       `LH : begin
        case(mem_addr_lsb)
        2'h0: mem_write_val={{16{mem_data[15]}}, mem_data[15:0]};
        2'h1: mem_write_val={{16{mem_data[15]}}, mem_data[15:0]};
        2'h2: mem_write_val = {{16{mem_data[31]}}, mem_data[31:16]};
        2'h3: mem_write_val = {{16{mem_data[31]}}, mem_data[31:16]};

        endcase
       end
        `LBU: begin
            case (mem_addr_lsb)
                2'h0: mem_write_val = {24'h0, mem_data[7:0]};
                2'h1: mem_write_val = {24'h0, mem_data[15:8]};
                2'h2: mem_write_val = {24'h0, mem_data[23:16]};
                2'h3: mem_write_val = {24'h0, mem_data[31:24]};
            endcase
       
       end
        `LHU: begin
            case (mem_addr_lsb)
                2'h0: mem_write_val = {16'h0, mem_data[15:0]};
                2'h1: mem_write_val = {16'h0, mem_data[15:0]};
                2'h2: mem_write_val = {16'h0, mem_data[31:16]};
                2'h3: mem_write_val = {16'h0, mem_data[31:16]};
            endcase
        end
    endcase
end


endmodule

sim_submodules/sim_build/load.vcd
$date
	Fri Jul  5 13:53:24 2024
$end
$version
	Icarus Verilog
$end
$timescale
	1ps
$end
$scope module load $end
$var wire 1 ! i_clk $end
$var wire 1 " i_rst $end
$var wire 32 # imm [31:0] $end
$var wire 3 $ load_control [2:0] $end
$var wire 32 % mem_data [31:0] $end
$var wire 1 & mem_rw_mode $end
$var wire 5 ' rd_in [4:0] $end
$var wire 32 ( rs1_val [31:0] $end
$var reg 1 ) ignore_curr_inst $end
$var reg 3 * load_control_reg [2:0] $end
$var reg 32 + mem_addr [31:0] $end
$var reg 2 , mem_addr_lsb [1:0] $end
$var reg 32 - mem_write_val [31:0] $end
$var reg 1 . next_state $end
$var reg 5 / rd_out [4:0] $end
$var reg 1 0 rd_write_control $end
$var reg 32 1 rd_write_val [31:0] $end
$var reg 1 2 stall_pc $end
$var reg 1 3 state $end
$upscope $end
$enddefinitions $end
$comment Show the parameter values. $end
$dumpall
$end
#0
$dumpvars
x3
x2
bx 1
x0
bx /
x.
b0 -
bx ,
bx +
bx *
x)
b0 (
b0 '
1&
b0 %
b0 $
b0 #
1"
0!
$end
#5000
b0 ,
b0 /
b0 *
1!
#5500
b0 +
02
0.
b0 1
00
0)
03
0"
0!
#6000
1!
#6500
0!
#7000
1"
1!
#7500
0!
#8000
1!
#8100
b11101101011101000101110000000 +
12
1.
b100 $
b110001110111 #
b11101101011100111111100001001 (
#8500
0!
#9000
b10011101 1
b10011101 -
b0 #
b0 (
b0 $
b1001000001110110101111010011101 %
b0 +
10
1)
02
0.
b100 *
13
1!
#9500
0!
#10000
b0 1
00
0)
b0 -
03
b0 *
1!
#10100
b10000101000010101011010000000 +
12
1.
b10 $
b10011 '
b0 %
b1100101 #
b10000101000010101011000011011 (
#10500
0!
#11000
b100110110001011 1
b100110110001011 -
b0 #
b0 (
b0 '
b0 $
b11001001001100000100110110001011 %
b0 +
10
1)
02
0.
b10011 /
b10 *
13
1!
#11500
0!
#12000
b0 1
00
0)
b0 -
03
b0 /
b0 *
1!
#12100
b11010010101011000101100010 +
12
1.
b100 $
b1010 '
b0 %
b1101001110 #
b11010010101010111000010100 (
#12500
0!
#13000
b1010100 1
b1010100 -
b0 #
b0 (
b0 '
b0 $
b110010010101001111011011011010 %
b0 +
10
1)
02
0.
b10 ,
b1010 /
b100 *
13
1!
#13500
0!
#14000
b0 1
00
0)
b0 -
03
b0 ,
b0 /
b0 *
1!
#14100
b11 '
b0 %
b111111011101 #
b100100000011100001000110011100 (
#14500
0!
#15000
1!
#15100
b101010001100101011111001100001 +
12
1.
b11 $
b1011 '
b111001011000 #
b101010001100101011000000001001 (
#15500
0!
#16000
b1001110100011101000100010000110 1
b1001110100011101000100010000110 -
b0 #
b0 (
b0 '
b0 $
b1001110100011101000100010000110 %
b0 +
10
1)
02
0.
13
b1 ,
b1011 /
b11 *
1!
#16500
0!
#17000
b0 -
b0 1
00
0)
b0 ,
b0 /
b0 *
03
1!
#17100
b10001000111100000000111001010 +
12
1.
b11 $
b11000 '
b0 %
b11110010101 #
b10001000111011111101000110101 (
#17500
0!
#18000
b10111000001010111101000101110010 1
b10111000001010111101000101110010 -
b0 #
b0 (
b0 '
b0 $
b10111000001010111101000101110010 %
b0 +
10
1)
02
0.
13
b10 ,
b11000 /
b11 *
1!
#18500
0!
#19000
b0 -
b0 1
00
0)
b0 ,
b0 /
b0 *
03
1!
#19100
b1000110101001011001010100000 +
12
1.
b100 $
b11100 '
b0 %
b11011101111 #
b1000110101001010101110110001 (
#19500
0!
#20000
b10110101 1
b10110101 -
b0 #
b0 (
b0 '
b0 $
b11100110111000011010010110101 %
b0 +
10
1)
02
0.
13
b11100 /
b100 *
1!
#20500
0!
#21000
b0 -
b0 1
00
0)
b0 /
b0 *
03
1!
#21100
b11010110101101001000010010010 +
12
1.
b11 $
b10101 '
b0 %
b10000111111 #
b11010110101101000110001010011 (
#21500
0!
#22000
b1011100010101100001010010100100 1
b1011100010101100001010010100100 -
b0 #
b0 (
b0 '
b0 $
b1011100010101100001010010100100 %
b0 +
10
1)
02
0.
13
b10 ,
b10101 /
b11 *
1!
#22500
0!
#23000
b0 -
b0 1
00
0)
b0 ,
b0 /
b0 *
03
1!
#23100
b100101001111111000100001000001 +
12
1.
b100 $
b1101 '
b0 %
b111111100011 #
b100101001111110111100001011110 (
#23500
0!
#24000
b10100010 1
b10100010 -
b0 #
b0 (
b0 '
b0 $
b10011100110011001010001011000111 %
b0 +
10
1)
02
0.
13
b1 ,
b1101 /
b100 *
1!
#24500
0!
#25000
b0 -
b0 1
00
0)
b0 ,
b0 /
b0 *
03
1!
#25100
b111100000001011000111110 +
12
1.
b100 $
b100 '
b0 %
b1010011101 #
b111100000001001110100001 (
#25500
0!
#26000
b11101010 1
b11101010 -
b0 #
b0 (
b0 '
b0 $
b1000111010100101110111001101 %
b0 +
10
1)
02
0.
13
b10 ,
b100 /
b100 *
1!
#26500
0!
#27000
b0 -
b0 1
00
0)
b0 ,
b0 /
b0 *
03
1!
#27100
b111111100011000101100110001101 +
12
1.
b10 $
b10100 '
b0 %
b1100010000 #
b111111100011000101011001111101 (
#27500
0!
#28000
b100000111011011 1
b100000111011011 -
b0 #
b0 (
b0 '
b0 $
b11101000000110100000111011011 %
b0 +
10
1)
02
0.
13
b1 ,
b10100 /
b10 *
1!
#28500
0!
#29000
b0 -
b0 1
00
0)
b0 ,
b0 /
b0 *
03
1!
#29100
b111000110000110011111010101 +
12
1.
b101 $
b1101 '
b0 %
b110011000100 #
b111000110000101101100010001 (
#29500
0!
#30000
b111100001010001 1
b111100001010001 -
b0 #
b0 (
b0 '
b0 $
b10010101011001010111100001010001 %
b0 +
10
1)
02
0.
13
b1 ,
b1101 /
b101 *
1!
#30500
0!
#31000
b0 -
b0 1
00
0)
b0 ,
b0 /
b0 *
03
1!
#31100
b1101011000011001110111100101 +
12
1.
b1 $
b1000 '
b0 %
b111000011001 #
b1101011000011000111111001100 (
#31500
0!
#32000
b11111111111111111111111111011001 1
b11111111111111111111111111011001 -
b0 #
b0 (
b0 '
b0 $
b111011100111001101100110100011 %
b0 +
10
1)
02
0.
13
b1 ,
b1000 /
b1 *
1!
#32500
0!
#33000
b0 -
b0 1
00
0)
b0 ,
b0 /
b0 *
03
1!
#33100
b1110 '
b0 %
b10011100 #
b1111110101000011101001110101 (
#33500
0!
#34000
1!
#34100
b111010000111000001100110000000 +
12
1.
b100 $
b11011 '
b101100001001 #
b111010000111000000111001110111 (
#34500
0!
#35000
b10000000 1
b10000000 -
b0 #
b0 (
b0 '
b0 $
b110001000111110101011010000000 %
b0 +
10
1)
02
0.
b11011 /
b100 *
13
1!
#35500
0!
#36000
b0 1
00
0)
b0 -
03
b0 /
b0 *
1!
#36100
b111110000101110110110010000000 +
12
1.
b1 $
b11001 '
b0 %
b100101001010 #
b111110000101110110001100110110 (
#36500
0!
#37000
b11111111111111111111111111001100 1
b11111111111111111111111111001100 -
b0 #
b0 (
b0 '
b0 $
b1010000000000000101101011001100 %
b0 +
10
1)
02
0.
b11001 /
b1 *
13
1!
#37500
0!
#38000
b0 1
00
0)
b0 -
03
b0 /
b0 *
1!
#38100
b11000000100011001111101001 +
12
1.
b10 $
b1010 '
b0 %
b111101100000 #
b11000000100010010010001001 (
#38500
0!
#39000
b11111111111111111010100110111100 1
b11111111111111111010100110111100 -
b0 #
b0 (
b0 '
b0 $
b110100101110101010100110111100 %
b0 +
10
1)
02
0.
b1 ,
b1010 /
b10 *
13
1!
#39500
0!
#40000
b0 1
00
0)
b0 -
03
b0 ,
b0 /
b0 *
1!
#40100
b111111000110000100100000111001 +
12
1.
b11 $
b1 '
b0 %
b100100100110 #
b111111000110000011111100010011 (
#40500
0!
#41000
b1011111001101100011110101001010 1
b1011111001101100011110101001010 -
b0 #
b0 (
b0 '
b0 $
b1011111001101100011110101001010 %
b0 +
10
1)
02
0.
b1 ,
b1 /
b11 *
13
1!
#41500
0!
#42000
b0 1
00
0)
b0 -
03
b0 ,
b0 /
b0 *
1!
#42100
b100101111001111100000100100010 +
12
1.
b1 $
b11110 '
b0 %
b11100111010 #
b100101111001111011100111101000 (
#42500
0!
#43000
b11101 1
b11101 -
b0 #
b0 (
b0 '
b0 $
b100100000111010110100010101001 %
b0 +
10
1)
02
0.
b10 ,
b11110 /
b1 *
13
1!
#43500
0!
#44000
b0 1
00
0)
b0 -
03
b0 ,
b0 /
b0 *
1!
#44100
b10 '
b0 %
b110010110110 #
b111011101110110010110111111110 (
#44500
0!
#45000
1!
#45100
b11100000100110011110101100111 +
12
1.
b11 $
b10101 '
b1110111111 #
b11100000100110011100110101000 (
#45500
0!
#46000
b1001001001101010110111100110110 1
b1001001001101010110111100110110 -
b0 #
b0 (
b0 '
b0 $
b1001001001101010110111100110110 %
b0 +
10
1)
02
0.
13
b11 ,
b10101 /
b11 *
1!
#46500
0!
#47000
b0 -
b0 1
00
0)
b0 ,
b0 /
b0 *
03
1!
#47100
b111000110101010010000110111011 +
12
1.
b10 $
b10010 '
b0 %
b111111101000 #
b111000110101010001000111010011 (
#47500
0!
#48000
b111011011110100 1
b111011011110100 -
b0 #
b0 (
b0 '
b0 $
b1110110111101001000000100001101 %
b0 +
10
1)
02
0.
13
b11 ,
b10010 /
b10 *
1!
#48500
0!
#49000
b0 -
b0 1
00
0)
b0 ,
b0 /
b0 *
03
1!
#49100
b110110010001100110101110110001 +
12
1.
b101 $
b11111 '
b0 %
b100001011010 #
b110110010001100110001101010111 (
#49500
0!
#50000
b1111100000011101 1
b1111100000011101 -
b0 #
b0 (
b0 '
b0 $
b111010101100111111100000011101 %
b0 +
10
1)
02
0.
13
b1 ,
b11111 /
b101 *
1!
#50500
0!
#51000
b0 -
b0 1
00
0)
b0 ,
b0 /
b0 *
03
1!
#51100
b100011110001010101110011101101 +
12
1.
b101 $
b10010 '
b0 %
b110001100010 #
b100011110001010101000010001011 (
#51500
0!
#52000
b1001100010110000 1
b1001100010110000 -
b0 #
b0 (
b0 '
b0 $
b1010111001110001001100010110000 %
b0 +
10
1)
02
0.
13
b1 ,
b10010 /
b101 *
1!
#52500
0!
#53000
b0 -
b0 1
00
0)
b0 ,
b0 /
b0 *
03
1!
#53100
b11010 '
b0 %
b11101010001 #
b1011001101101011101010110110 (
#53500
0!
#54000
1!
#54100
b101111010001110000000110010001 +
12
1.
b101 $
b10111 '
b101001010101 #
b101111010001101111011100111100 (
#54500
0!
#55000
b1101001111111100 1
b1101001111111100 -
b0 #
b0 (
b0 '
b0 $
b101000101010111101001111111100 %
b0 +
10
1)
02
0.
b1 ,
b10111 /
b101 *
13
1!
#55500
0!
#56000
b0 1
00
0)
b0 -
03
b0 ,
b0 /
b0 *
1!
#56100
b111010100001001110101111011101 +
12
1.
b11 $
b10001 '
b0 %
b111001011101 #
b111010100001001101110110000000 (
#56500
0!
#57000
b10011111100001011000110010111101 1
b10011111100001011000110010111101 -
b0 #
b0 (
b0 '
b0 $
b10011111100001011000110010111101 %
b0 +
10
1)
02
0.
b1 ,
b10001 /
b11 *
13
1!
#57500
0!
#58000
b0 1
00
0)
b0 -
03
b0 ,
b0 /
b0 *
1!
#58100
b101011001001100100001111010011 +
12
1.
b100 $
b1001 '
b0 %
b10111111111 #
b101011001001100011110111010100 (
#58500
0!
#59000
b1010000 1
b1010000 -
b0 #
b0 (
b0 '
b0 $
b1010000011010010010110000001000 %
b0 +
10
1)
02
0.
b11 ,
b1001 /
b100 *
13
1!
#59500
0!
#60000
b0 1
00
0)
b0 -
03
b0 ,
b0 /
b0 *
1!
#60100
b100 '
b0 %
b10110110 #
b110100110111110001100101100110 (
#60500
0!
#61000
1!
#61100
b1010111010011111010110010101 +
12
1.
b101 $
b10010 '
b101110001011 #
b1010111010011110101000001010 (
#61500
0!
#62000
b1001000110100011 1
b1001000110100011 -
b0 #
b0 (
b0 '
b0 $
b1110101011100011001000110100011 %
b0 +
10
1)
02
0.
13
b1 ,
b10010 /
b101 *
1!
#62500
0!
#63000
b0 -
b0 1
00
0)
b0 ,
b0 /
b0 *
03
1!
#63100
b100010001010111010001000000 +
12
1.
b10 $
b11100 '
b0 %
b100011000010 #
b100010001010110101101111110 (
#63500
0!
#64000
b1010111001011 1
b1010111001011 -
b0 #
b0 (
b0 '
b0 $
b110111010011110001010111001011 %
b0 +
10
1)
02
0.
13
b11100 /
b10 *
1!
#64500
0!
#65000
b0 -
b0 1
00
0)
b0 /
b0 *
03
1!
#65100
b11110010100001101111101000101 +
12
1.
b100 $
b10000 '
b0 %
b11010010011 #
b11110010100001101100010110010 (
#65500
0!
#66000
b10110000 1
b10110000 -
b0 #
b0 (
b0 '
b0 $
b11111101000111001011000001101000 %
b0 +
10
1)
02
0.
13
b1 ,
b10000 /
b100 *
1!
#66500
0!
#67000
b0 -
b0 1
00
0)
b0 ,
b0 /
b0 *
03
1!
#67100
b1100 '
b0 %
b111010111010 #
b1110100011011001011010110100 (
#67500
0!
#68000
1!
#68100
b111010010010000000100111010011 +
12
1.
b10 $
b10011 '
b110011101111 #
b111010010001111111110011100100 (
#68500
0!
#69000
b11111111111111111110011010110010 1
b11111111111111111110011010110010 -
b0 #
b0 (
b0 '
b0 $
b11100110101100101110110100001011 %
b0 +
10
1)
02
0.
b11 ,
b10011 /
b10 *
13
1!
#69500
0!
#70000
b0 1
00
0)
b0 -
03
b0 ,
b0 /
b0 *
1!
#70100
b111111111100011101000111110101 +
12
1.
b11 $
b10000 '
b0 %
b110001011101 #
b111111111100011100010110011000 (
#70500
0!
#71000
b10110100111000100110001010010111 1
b10110100111000100110001010010111 -
b0 #
b0 (
b0 '
b0 $
b10110100111000100110001010010111 %
b0 +
10
1)
02
0.
b1 ,
b10000 /
b11 *
13
1!
#71500
0!
#72000
b0 1
00
0)
b0 -
03
b0 ,
b0 /
b0 *
1!
#72100
b11100000101011111010000001 +
12
1.
b101 $
b1 '
b0 %
b10010010110 #
b11100000101011100111101011 (
#72500
0!
#73000
b111010111010110 1
b111010111010110 -
b0 #
b0 (
b0 '
b0 $
b1111001010000100111010111010110 %
b0 +
10
1)
02
0.
b1 ,
b1 /
b101 *
13
1!
#73500
0!
#74000
b0 1
00
0)
b0 -
03
b0 ,
b0 /
b0 *
1!
#74100
b10000011111011110101011001000 +
12
1.
b1 $
b11100 '
b0 %
b10001100010 #
b10000011111011110011001100110 (
#74500
0!
#75000
b11111111111111111111111110110001 1
b11111111111111111111111110110001 -
b0 #
b0 (
b0 '
b0 $
b10001100110010110010010110110001 %
b0 +
10
1)
02
0.
b11100 /
b1 *
13
1!
#75500
0!
#76000
b0 1
00
0)
b0 -
03
b0 /
b0 *
1!
#76100
b10100011010011011001101101101 +
12
1.
b100 $
b10110 '
b0 %
b101011000111 #
b10100011010011010100010100110 (
#76500
0!
#77000
b101110 1
b101110 -
b0 #
b0 (
b0 '
b0 $
b11010001011111110010111000011010 %
b0 +
10
1)
02
0.
b1 ,
b10110 /
b100 *
13
1!
#77500
0!
#78000
b0 1
00
0)
b0 -
03
b0 ,
b0 /
b0 *
1!
#78100
b11101100101111111010101111011 +
12
1.
b101 $
b1110 '
b0 %
b1000110000 #
b11101100101111111001101001011 (
#78500
0!
#79000
b1101001101101101 1
b1101001101101101 -
b0 #
b0 (
b0 '
b0 $
b11010011011011011010010000001100 %
b0 +
10
1)
02
0.
b11 ,
b1110 /
b101 *
13
1!
#79500
0!
#80000
b0 1
00
0)
b0 -
03
b0 ,
b0 /
b0 *
1!
#80100
b10001 '
b0 %
b110011011011 #
b100000010100011010000010001110 (
#80500
0!
#81000
1!
#81100
b111010111100110101000000001010 +
12
1.
b10 $
b111 '
b10101001 #
b111010111100110100111101100001 (
#81500
0!
#82000
b11111111111111111100100001010001 1
b11111111111111111100100001010001 -
b0 #
b0 (
b0 '
b0 $
b11001000010100010010101100100010 %
b0 +
10
1)
02
0.
13
b10 ,
b111 /
b10 *
1!
#82500
0!
#83000
b0 -
b0 1
00
0)
b0 ,
b0 /
b0 *
03
1!
#83100
b10000 '
b0 %
b11001110111 #
b1010001000001000010110111 (
#83500
0!
#84000
1!
#84100
b111111110101111111000110011000 +
12
1.
b11 $
b1 '
b101100000100 #
b111111110101111110011010010100 (
#84500
0!
#85000
b1110011101100000101001111011011 1
b1110011101100000101001111011011 -
b0 #
b0 (
b0 '
b0 $
b1110011101100000101001111011011 %
b0 +
10
1)
02
0.
b1 /
b11 *
13
1!
#85500
0!
#86000
b0 1
00
0)
b0 -
03
b0 /
b0 *
1!
#86100
b100011011011001010100000011011 +
12
1.
b10 $
b10001 '
b0 %
b101100011010 #
b100011011011001001110100000001 (
#86500
0!
#87000
b11111111111111111100001010001101 1
b11111111111111111100001010001101 -
b0 #
b0 (
b0 '
b0 $
b11000010100011011110011100010011 %
b0 +
10
1)
02
0.
b11 ,
b10001 /
b10 *
13
1!
#87500
0!
#88000
b0 1
00
0)
b0 -
03
b0 ,
b0 /
b0 *
1!
#88100
b10100000101000001001000111101 +
12
1.
b1 $
b10111 '
b0 %
b100000001110 #
b10100000101000000101000101111 (
#88500
0!
#89000
b1100000 1
b1100000 -
b0 #
b0 (
b0 '
b0 $
b111100011010010110000010001101 %
b0 +
10
1)
02
0.
b1 ,
b10111 /
b1 *
13
1!
#89500
0!
#90000
b0 1
00
0)
b0 -
03
b0 ,
b0 /
b0 *
1!
#90100
b11001100100111011001001011111 +
12
1.
b10 $
b11111 '
b0 %
b10100011110 #
b11001100100111010110101000001 (
#90500
0!
#91000
b11111111111111111110110101000011 1
b11111111111111111110110101000011 -
b0 #
b0 (
b0 '
b0 $
b11101101010000110101001101110110 %
b0 +
10
1)
02
0.
b11 ,
b11111 /
b10 *
13
1!
#91500
0!
#92000
b0 1
00
0)
b0 -
03
b0 ,
b0 /
b0 *
1!
#92100
b1111110110001101111111010001 +
12
1.
b11 $
b10111 '
b0 %
b111100111110 #
b1111110110001101000010010011 (
#92500
0!
#93000
b1100110110011101110011100101011 1
b1100110110011101110011100101011 -
b0 #
b0 (
b0 '
b0 $
b1100110110011101110011100101011 %
b0 +
10
1)
02
0.
b1 ,
b10111 /
b11 *
13
1!
#93500
0!
#94000
b0 1
00
0)
b0 -
03
b0 ,
b0 /
b0 *
1!
#94100
b110000000101001010011111000101 +
12
1.
b101 $
b10101 '
b0 %
b10000101 #
b110000000101001010011101000000 (
#94500
0!
#95000
b11101001001100 1
b11101001001100 -
b0 #
b0 (
b0 '
b0 $
b11101010011001100011101001001100 %
b0 +
10
1)
02
0.
b1 ,
b10101 /
b101 *
13
1!
#95500
0!
#96000
b0 1
00
0)
b0 -
03
b0 ,
b0 /
b0 *
1!
#96100
b111010001001110001011011110100 +
12
1.
b1 $
b10111 '
b0 %
b10010101110 #
b111010001001110001001001000110 (
#96500
0!
#97000
b110010 1
b110010 -
b0 #
b0 (
b0 '
b0 $
b10001101110110000010101000110010 %
b0 +
10
1)
02
0.
b10111 /
b1 *
13
1!
#97500
0!
#98000
b0 1
00
0)
b0 -
03
b0 /
b0 *
1!
#98100
b10111111100010000000111100101 +
12
1.
b101 $
b10110 '
b0 %
b110011010101 #
b10111111100001111010100010000 (
#98500
0!
#99000
b11110100010011 1
b11110100010011 -
b0 #
b0 (
b0 '
b0 $
b10001010010001110011110100010011 %
b0 +
10
1)
02
0.
b1 ,
b10110 /
b101 *
13
1!
#99500
0!
#100000
b0 1
00
0)
b0 -
03
b0 ,
b0 /
b0 *
1!
#100100
b11111010100010101101111101010 +
12
1.
b1 $
b10 '
b0 %
b101100000011 #
b11111010100010101000011100111 (
#100500
0!
#101000
b1011101 1
b1011101 -
b0 #
b0 (
b0 '
b0 $
b111100010111010000111110011110 %
b0 +
10
1)
02
0.
b10 ,
b10 /
b1 *
13
1!
#101500
0!
#102000
b0 1
00
0)
b0 -
03
b0 ,
b0 /
b0 *
1!
#102100
b1011101111100100100110000 +
12
1.
b11 $
b10111 '
b0 %
b111100110110 #
b1011101111011100111111010 (
#102500
0!
#103000
b11110111100011101111010001111111 1
b11110111100011101111010001111111 -
b0 #
b0 (
b0 '
b0 $
b11110111100011101111010001111111 %
b0 +
10
1)
02
0.
b10111 /
b11 *
13
1!
#103500
0!
#104000
b0 1
00
0)
b0 -
03
b0 /
b0 *
1!
#104100
b10111110111001011111110110001 +
12
1.
b11 $
b10100 '
b0 %
b1011101100 #
b10111110111001011110011000101 (
#104500
0!
#105000
b11100010011100001100011001100111 1
b11100010011100001100011001100111 -
b0 #
b0 (
b0 '
b0 $
b11100010011100001100011001100111 %
b0 +
10
1)
02
0.
b1 ,
b10100 /
b11 *
13
1!
#105500
0!
#106000
b0 1
00
0)
b0 -
03
b0 ,
b0 /
b0 *
1!
#106100
b1011101111010000011100001010 +
12
1.
b10 $
b10000 '
b0 %
b10010111111 #
b1011101111010000001001001011 (
#106500
0!
#107000
b11111111111111111010110000101110 1
b11111111111111111010110000101110 -
b0 #
b0 (
b0 '
b0 $
b10101100001011101010000100001111 %
b0 +
10
1)
02
0.
b10 ,
b10000 /
b10 *
13
1!
#107500
0!
#108000
b0 1
00
0)
b0 -
03
b0 ,
b0 /
b0 *
1!
#108100
b110100110111101010011000001111 +
12
1.
b100 $
b1011 '
b0 %
b101010010011 #
b110100110111101001101101111100 (
#108500
0!
#109000
b11010011 1
b11010011 -
b0 #
b0 (
b0 '
b0 $
b11010011010100110110001001000001 %
b0 +
10
1)
02
0.
b11 ,
b1011 /
b100 *
13
1!
#109500
0!
#110000
b0 1
00
0)
b0 -
03
b0 ,
b0 /
b0 *
1!
#110100
b101111101111001010110100101000 +
12
1.
b10 $
b1000 '
b0 %
b100001101100 #
b101111101111001010010010111100 (
#110500
0!
#111000
b101111101010101 1
b101111101010101 -
b0 #
b0 (
b0 '
b0 $
b10010010110111100101111101010101 %
b0 +
10
1)
02
0.
b1000 /
b10 *
13
1!
#111500
0!
#112000
b0 1
00
0)
b0 -
03
b0 /
b0 *
1!
#112100
b10111110100100111010001011100 +
12
1.
b1 $
b1000 '
b0 %
b110010001001 #
b10111110100100110011111010011 (
#112500
0!
#113000
b11111111111111111111111110110010 1
b11111111111111111111111110110010 -
b0 #
b0 (
b0 '
b0 $
b1000111000101000110011110110010 %
b0 +
10
1)
02
0.
b1000 /
b1 *
13
1!
#113500
0!
#114000
b0 1
00
0)
b0 -
03
b0 /
b0 *
1!
#114100
b11101110000000110110100101111 +
12
1.
b10 $
b0 %
b11000100001 #
b11101110000000110011100001110 (
#114500
0!
#115000
b1100111111011 1
b1100111111011 -
b0 #
b0 (
b0 $
b11001111110110001010101111010 %
b0 +
10
1)
02
0.
b11 ,
b10 *
13
1!
#115500
0!
#116000
b0 1
00
0)
b0 -
03
b0 ,
b0 *
1!
#116100
b1101110101110110111100100111 +
12
1.
b100 $
b1001 '
b0 %
b10010011010 #
b1101110101110110101010001101 (
#116500
0!
#117000
b10001001 1
b10001001 -
b0 #
b0 (
b0 '
b0 $
b10001001000011000011010100110000 %
b0 +
10
1)
02
0.
b11 ,
b1001 /
b100 *
13
1!
#117500
0!
#118000
b0 1
00
0)
b0 -
03
b0 ,
b0 /
b0 *
1!
#118100
b11100110010011101011110000000 +
12
1.
b1 $
b10100 '
b0 %
b111100110000 #
b11100110010011100100001010000 (
#118500
0!
#119000
b1001 1
b1001 -
b0 #
b0 (
b0 '
b0 $
b11001010100101100011100000001001 %
b0 +
10
1)
02
0.
b10100 /
b1 *
13
1!
#119500
0!
#120000
b0 1
00
0)
b0 -
03
b0 /
b0 *
1!
#120100
b1000 '
b0 %
b10011101111 #
b11111000000101111000110110110 (
#120500
0!
#121000
1!
#121100
b111010001010100101110001110001 +
12
1.
b100 $
b10 '
b110001100001 #
b111010001010100101000000010000 (
#121500
0!
#122000
b11100110 1
b11100110 -
b0 #
b0 (
b0 '
b0 $
b11101101010111111110011010111011 %
b0 +
10
1)
02
0.
13
b1 ,
b10 /
b100 *
1!
#122500
0!
#123000
b0 -
b0 1
00
0)
b0 ,
b0 /
b0 *
03
1!
#123100
b11001 '
b0 %
b111101010100 #
b101010011011010001010001110011 (
#123500
0!
#124000
1!
#124100
b1101 '
b100001011010 #
b11000011110001100001011100111 (
#124500
0!
#125000
1!
#125100
b111110110011101110100110100101 +
12
1.
b100 $
b10 '
b111101101010 #
b111110110011101101101000111011 (
#125500
0!
#126000
b1110000 1
b1110000 -
b0 #
b0 (
b0 '
b0 $
b10001111011100000111000010101010 %
b0 +
10
1)
02
0.
13
b1 ,
b10 /
b100 *
1!
#126500
0!
#127000
b0 -
b0 1
00
0)
b0 ,
b0 /
b0 *
03
1!
#127100
b11101110000011111100000011011 +
12
1.
b101 $
b0 %
b110111110101 #
b11101110000011110101000100110 (
#127500
0!
#128000
b1001011110101000 1
b1001011110101000 -
b0 #
b0 (
b0 $
b10010111101010001011111110001001 %
b0 +
10
1)
02
0.
13
b11 ,
b101 *
1!
#128500
0!
#129000
b0 -
b0 1
00
0)
b0 ,
b0 *
03
1!
#129100
b1100110110010111101011101000 +
12
1.
b100 $
b10111 '
b0 %
b111111010100 #
b1100110110010110101100010100 (
#129500
0!
#130000
b101111 1
b101111 -
b0 #
b0 (
b0 '
b0 $
b1101101101100010110010100101111 %
b0 +
10
1)
02
0.
13
b10111 /
b100 *
1!
#130500
0!
#131000
b0 -
b0 1
00
0)
b0 /
b0 *
03
1!
#131100
b10001000000011010111010110001 +
12
1.
b10 $
b1011 '
b0 %
b100011000100 #
b10001000000011010010111101101 (
#131500
0!
#132000
b11111111111111111000010011101001 1
b11111111111111111000010011101001 -
b0 #
b0 (
b0 '
b0 $
b10100110001110111000010011101001 %
b0 +
10
1)
02
0.
13
b1 ,
b1011 /
b10 *
1!
#132500
0!
#133000
b0 -
b0 1
00
0)
b0 ,
b0 /
b0 *
03
1!
#133100
b100110010001100101111010000111 +
12
1.
b11 $
b11010 '
b0 %
b1010100110 #
b100110010001100101101111100001 (
#133500
0!
#134000
b10010101111010101000010011100100 1
b10010101111010101000010011100100 -
b0 #
b0 (
b0 '
b0 $
b10010101111010101000010011100100 %
b0 +
10
1)
02
0.
13
b11 ,
b11010 /
b11 *
1!
#134500
0!
#135000
b0 -
b0 1
00
0)
b0 ,
b0 /
b0 *
03
1!
#135100
b111001001110110111001101101000 +
12
1.
b10 $
b1111 '
b0 %
b1000010111 #
b111001001110110111000101010001 (
#135500
0!
#136000
b10110011001111 1
b10110011001111 -
b0 #
b0 (
b0 '
b0 $
b1011101011100010010110011001111 %
b0 +
10
1)
02
0.
13
b1111 /
b10 *
1!
#136500
0!
